Workbook

Sheet Historical
A1: Year | B1: Revenue | C1: Operating income | D1: Net income attributable | E1: Operating cash flow | F1: Capex | G1: Free cash flow (formula) | H1: Depreciation and amortisation | I1: Owner earnings proxy (formula) | J1: Dividends paid | K1: Other investing outflow (proxy) | L1: Invested capital | M1: Pre-tax ROIC % (formula)
A2: 2016 | B2: 2125 | C2: 339 | D2: 207 | E2: 491 | F2: 19 | G2: =E2-F2 | H2: 213 | I2: =D2+H2-F2 | J2: 85 | K2: 176 | L2: 447 | M2: =IF(ROW()=2,"n/a",C2/AVERAGE(L1:L2)*100)
A3: 2017 | B3: 2479 | C3: 391 | D3: 222 | E3: 528 | F3: 20 | G3: =E3-F3 | H3: 253 | I3: =D3+H3-F3 | J3: 85 | K3: 230 | L3: 448 | M3: =IF(ROW()=2,"n/a",C3/AVERAGE(L2:L3)*100)
A4: 2018 | B4: 3060 | C4: 478 | D4: 379 | E4: 662 | F4: 25 | G4: =E4-F4 | H4: 306 | I4: =D4+H4-F4 | J4: 85 | K4: 483 | L4: 645 | M4: =IF(ROW()=2,"n/a",C4/AVERAGE(L3:L4)*100)
A5: 2019 | B5: 3489 | C5: 511 | D5: 333 | E5: 767 | F5: 34 | G5: =E5-F5 | H5: 423 | I5: =D5+H5-F5 | J5: 509 | K5: 510 | L5: 1191 | M5: =IF(ROW()=2,"n/a",C5/AVERAGE(L4:L5)*100)
A6: 2020 | B6: 3969 | C6: 682 | D6: 436 | E6: 1186 | F6: 25 | G6: =E6-F6 | H6: 508 | I6: =D6+H6-F6 | J6: 85 | K6: 487 | L6: 1119 | M6: =IF(ROW()=2,"n/a",C6/AVERAGE(L5:L6)*100)
A7: 2021 | B7: 5106 | C7: 870 | D7: 310 | E7: 1300 | F7: 29 | G7: =E7-F7 | H7: 639 | I7: =D7+H7-F7 | J7: 85 | K7: 1200 | L7: 2101 | M7: =IF(ROW()=2,"n/a",C7/AVERAGE(L6:L7)*100)
A8: 2022 | B8: 6622 | C8: 920 | D8: 512 | E8: 1297 | F8: 41 | G8: =E8-F8 | H8: 819 | I8: =D8+H8-F8 | J8: 92 | K8: 1700 | L8: 3324 | M8: =IF(ROW()=2,"n/a",C8/AVERAGE(L7:L8)*100)
A9: 2023 | B9: 8407 | C9: 1182 | D9: 565 | E9: 1779 | F9: 42 | G9: =E9-F9 | H9: 1020 | I9: =D9+H9-F9 | J9: 85 | K9: 1600 | L9: 4347 | M9: =IF(ROW()=2,"n/a",C9/AVERAGE(L8:L9)*100)
A10: 2024 | B10: 10066 | C10: 1471 | D10: 731 | E10: 2196 | F10: 67 | G10: =E10-F10 | H10: 1230 | I10: =D10+H10-F10 | J10: 85 | K10: 1500 | L10: 5811 | M10: =IF(ROW()=2,"n/a",C10/AVERAGE(L9:L10)*100)
A11: 2025 | B11: 11623 | C11: 1928 | D11: 512 | E11: 2732 | F11: 68 | G11: =E11-F11 | H11: 1410 | I11: =D11+H11-F11 | J11: 85 | K11: 1800 | L11: 6415 | M11: =IF(ROW()=2,"n/a",C11/AVERAGE(L10:L11)*100)
A13: Notes: USD millions. Revenue, operating income, net income, operating cash flow, capex, dividends and debt/cash from StockAnalysis, AlphaSpread, MacroTrends and company reports, as listed in the README. Other investing outflow is a proxy for acquisition spending, not a verified acquisition-only line. ROIC is pre-tax operating income divided by average invested capital. 2016 ROIC is shown as n/a because 2015 invested capital was not verified on the same basis.

Sheet DCF
A1: DCF inputs
A2: 2025 free cash flow (USD millions) | B2: 2664
A3: Shares outstanding (millions) | B3: 21.19
A4: Net debt at 31 Dec 2025 (USD millions) | B4: 2646
A5: Share price, 23 Oct 2026 (CAD) | B5: 3395
A6: FX, CAD per USD, 23 Oct 2026 | B6: 1.4
A8: Case | B8: FCF growth | C8: Discount rate | D8: Terminal growth | E8: Value per share (CAD, formula)
A9: Base | B9: 0.08 | C9: 0.09 | D9: 0.03 | E9: =(SUM(Forecast!C2:C6)+Forecast!D6-B4)/B3*B6
A10: Optimistic | B10: 0.12 | C10: 0.08 | D10: 0.035 | E10: =(SUM(Forecast!C7:C11)+Forecast!D11-B4)/B3*B6
A11: Pessimistic | B11: 0.04 | C11: 0.105 | D11: 0.02 | E11: =(SUM(Forecast!C12:C16)+Forecast!D16-B4)/B3*B6

Sheet Forecast
A1: Case | B1: Year | C1: PV of FCF (USD millions, formula) | D1: PV of terminal value (USD millions, formula)
A2: Base | B2: 2026 | C2: =DCF!$B$2*(1+DCF!B9)^1/(1+DCF!C9)^1
A3: Base | B3: 2027 | C3: =DCF!$B$2*(1+DCF!B9)^2/(1+DCF!C9)^2
A4: Base | B4: 2028 | C4: =DCF!$B$2*(1+DCF!B9)^3/(1+DCF!C9)^3
A5: Base | B5: 2029 | C5: =DCF!$B$2*(1+DCF!B9)^4/(1+DCF!C9)^4
A6: Base | B6: 2030 | C6: =DCF!$B$2*(1+DCF!B9)^5/(1+DCF!C9)^5 | D6: =(DCF!$B$2*(1+DCF!B9)^5*(1+DCF!D9)/(DCF!C9-DCF!D9))/(1+DCF!C9)^5
A7: Optimistic | B7: 2026 | C7: =DCF!$B$2*(1+DCF!B10)^1/(1+DCF!C10)^1
A8: Optimistic | B8: 2027 | C8: =DCF!$B$2*(1+DCF!B10)^2/(1+DCF!C10)^2
A9: Optimistic | B9: 2028 | C9: =DCF!$B$2*(1+DCF!B10)^3/(1+DCF!C10)^3
A10: Optimistic | B10: 2029 | C10: =DCF!$B$2*(1+DCF!B10)^4/(1+DCF!C10)^4
A11: Optimistic | B11: 2030 | C11: =DCF!$B$2*(1+DCF!B10)^5/(1+DCF!C10)^5 | D11: =(DCF!$B$2*(1+DCF!B10)^5*(1+DCF!D10)/(DCF!C10-DCF!D10))/(1+DCF!C10)^5
A12: Pessimistic | B12: 2026 | C12: =DCF!$B$2*(1+DCF!B11)^1/(1+DCF!C11)^1
A13: Pessimistic | B13: 2027 | C13: =DCF!$B$2*(1+DCF!B11)^2/(1+DCF!C11)^2
A14: Pessimistic | B14: 2028 | C14: =DCF!$B$2*(1+DCF!B11)^3/(1+DCF!C11)^3
A15: Pessimistic | B15: 2029 | C15: =DCF!$B$2*(1+DCF!B11)^4/(1+DCF!C11)^4
A16: Pessimistic | B16: 2030 | C16: =DCF!$B$2*(1+DCF!B11)^5/(1+DCF!C11)^5 | D16: =(DCF!$B$2*(1+DCF!B11)^5*(1+DCF!D11)/(DCF!C11-DCF!D11))/(1+DCF!C11)^5

Sheet Sensitivity
A1: Value per share (CAD) at terminal growth 3%. Rows: FCF growth. Columns: discount rate.
B2: 0.08 | C2: 0.09 | D2: 0.1 | E2: 0.11
A3: 0.04 | B3: =( DCF!$B$2*(1+$A3)^1/(1+0.08)^1+DCF!$B$2*(1+$A3)^2/(1+0.08)^2+DCF!$B$2*(1+$A3)^3/(1+0.08)^3+DCF!$B$2*(1+$A3)^4/(1+0.08)^4+DCF!$B$2*(1+$A3)^5/(1+0.08)^5 +(DCF!$B$2*(1+$A3)^5*1.03/(0.08-0.03))/(1+0.08)^5-DCF!$B$4)/DCF!$B$3*DCF!$B$6 | C3: =( DCF!$B$2*(1+$A3)^1/(1+0.09)^1+DCF!$B$2*(1+$A3)^2/(1+0.09)^2+DCF!$B$2*(1+$A3)^3/(1+0.09)^3+DCF!$B$2*(1+$A3)^4/(1+0.09)^4+DCF!$B$2*(1+$A3)^5/(1+0.09)^5 +(DCF!$B$2*(1+$A3)^5*1.03/(0.09-0.03))/(1+0.09)^5-DCF!$B$4)/DCF!$B$3*DCF!$B$6 | D3: =( DCF!$B$2*(1+$A3)^1/(1+0.1)^1+DCF!$B$2*(1+$A3)^2/(1+0.1)^2+DCF!$B$2*(1+$A3)^3/(1+0.1)^3+DCF!$B$2*(1+$A3)^4/(1+0.1)^4+DCF!$B$2*(1+$A3)^5/(1+0.1)^5 +(DCF!$B$2*(1+$A3)^5*1.03/(0.1-0.03))/(1+0.1)^5-DCF!$B$4)/DCF!$B$3*DCF!$B$6 | E3: =( DCF!$B$2*(1+$A3)^1/(1+0.11)^1+DCF!$B$2*(1+$A3)^2/(1+0.11)^2+DCF!$B$2*(1+$A3)^3/(1+0.11)^3+DCF!$B$2*(1+$A3)^4/(1+0.11)^4+DCF!$B$2*(1+$A3)^5/(1+0.11)^5 +(DCF!$B$2*(1+$A3)^5*1.03/(0.11-0.03))/(1+0.11)^5-DCF!$B$4)/DCF!$B$3*DCF!$B$6
A4: 0.06 | B4: =( DCF!$B$2*(1+$A4)^1/(1+0.08)^1+DCF!$B$2*(1+$A4)^2/(1+0.08)^2+DCF!$B$2*(1+$A4)^3/(1+0.08)^3+DCF!$B$2*(1+$A4)^4/(1+0.08)^4+DCF!$B$2*(1+$A4)^5/(1+0.08)^5 +(DCF!$B$2*(1+$A4)^5*1.03/(0.08-0.03))/(1+0.08)^5-DCF!$B$4)/DCF!$B$3*DCF!$B$6 | C4: =( DCF!$B$2*(1+$A4)^1/(1+0.09)^1+DCF!$B$2*(1+$A4)^2/(1+0.09)^2+DCF!$B$2*(1+$A4)^3/(1+0.09)^3+DCF!$B$2*(1+$A4)^4/(1+0.09)^4+DCF!$B$2*(1+$A4)^5/(1+0.09)^5 +(DCF!$B$2*(1+$A4)^5*1.03/(0.09-0.03))/(1+0.09)^5-DCF!$B$4)/DCF!$B$3*DCF!$B$6 | D4: =( DCF!$B$2*(1+$A4)^1/(1+0.1)^1+DCF!$B$2*(1+$A4)^2/(1+0.1)^2+DCF!$B$2*(1+$A4)^3/(1+0.1)^3+DCF!$B$2*(1+$A4)^4/(1+0.1)^4+DCF!$B$2*(1+$A4)^5/(1+0.1)^5 +(DCF!$B$2*(1+$A4)^5*1.03/(0.1-0.03))/(1+0.1)^5-DCF!$B$4)/DCF!$B$3*DCF!$B$6 | E4: =( DCF!$B$2*(1+$A4)^1/(1+0.11)^1+DCF!$B$2*(1+$A4)^2/(1+0.11)^2+DCF!$B$2*(1+$A4)^3/(1+0.11)^3+DCF!$B$2*(1+$A4)^4/(1+0.11)^4+DCF!$B$2*(1+$A4)^5/(1+0.11)^5 +(DCF!$B$2*(1+$A4)^5*1.03/(0.11-0.03))/(1+0.11)^5-DCF!$B$4)/DCF!$B$3*DCF!$B$6
A5: 0.08 | B5: =( DCF!$B$2*(1+$A5)^1/(1+0.08)^1+DCF!$B$2*(1+$A5)^2/(1+0.08)^2+DCF!$B$2*(1+$A5)^3/(1+0.08)^3+DCF!$B$2*(1+$A5)^4/(1+0.08)^4+DCF!$B$2*(1+$A5)^5/(1+0.08)^5 +(DCF!$B$2*(1+$A5)^5*1.03/(0.08-0.03))/(1+0.08)^5-DCF!$B$4)/DCF!$B$3*DCF!$B$6 | C5: =( DCF!$B$2*(1+$A5)^1/(1+0.09)^1+DCF!$B$2*(1+$A5)^2/(1+0.09)^2+DCF!$B$2*(1+$A5)^3/(1+0.09)^3+DCF!$B$2*(1+$A5)^4/(1+0.09)^4+DCF!$B$2*(1+$A5)^5/(1+0.09)^5 +(DCF!$B$2*(1+$A5)^5*1.03/(0.09-0.03))/(1+0.09)^5-DCF!$B$4)/DCF!$B$3*DCF!$B$6 | D5: =( DCF!$B$2*(1+$A5)^1/(1+0.1)^1+DCF!$B$2*(1+$A5)^2/(1+0.1)^2+DCF!$B$2*(1+$A5)^3/(1+0.1)^3+DCF!$B$2*(1+$A5)^4/(1+0.1)^4+DCF!$B$2*(1+$A5)^5/(1+0.1)^5 +(DCF!$B$2*(1+$A5)^5*1.03/(0.1-0.03))/(1+0.1)^5-DCF!$B$4)/DCF!$B$3*DCF!$B$6 | E5: =( DCF!$B$2*(1+$A5)^1/(1+0.11)^1+DCF!$B$2*(1+$A5)^2/(1+0.11)^2+DCF!$B$2*(1+$A5)^3/(1+0.11)^3+DCF!$B$2*(1+$A5)^4/(1+0.11)^4+DCF!$B$2*(1+$A5)^5/(1+0.11)^5 +(DCF!$B$2*(1+$A5)^5*1.03/(0.11-0.03))/(1+0.11)^5-DCF!$B$4)/DCF!$B$3*DCF!$B$6
A6: 0.1 | B6: =( DCF!$B$2*(1+$A6)^1/(1+0.08)^1+DCF!$B$2*(1+$A6)^2/(1+0.08)^2+DCF!$B$2*(1+$A6)^3/(1+0.08)^3+DCF!$B$2*(1+$A6)^4/(1+0.08)^4+DCF!$B$2*(1+$A6)^5/(1+0.08)^5 +(DCF!$B$2*(1+$A6)^5*1.03/(0.08-0.03))/(1+0.08)^5-DCF!$B$4)/DCF!$B$3*DCF!$B$6 | C6: =( DCF!$B$2*(1+$A6)^1/(1+0.09)^1+DCF!$B$2*(1+$A6)^2/(1+0.09)^2+DCF!$B$2*(1+$A6)^3/(1+0.09)^3+DCF!$B$2*(1+$A6)^4/(1+0.09)^4+DCF!$B$2*(1+$A6)^5/(1+0.09)^5 +(DCF!$B$2*(1+$A6)^5*1.03/(0.09-0.03))/(1+0.09)^5-DCF!$B$4)/DCF!$B$3*DCF!$B$6 | D6: =( DCF!$B$2*(1+$A6)^1/(1+0.1)^1+DCF!$B$2*(1+$A6)^2/(1+0.1)^2+DCF!$B$2*(1+$A6)^3/(1+0.1)^3+DCF!$B$2*(1+$A6)^4/(1+0.1)^4+DCF!$B$2*(1+$A6)^5/(1+0.1)^5 +(DCF!$B$2*(1+$A6)^5*1.03/(0.1-0.03))/(1+0.1)^5-DCF!$B$4)/DCF!$B$3*DCF!$B$6 | E6: =( DCF!$B$2*(1+$A6)^1/(1+0.11)^1+DCF!$B$2*(1+$A6)^2/(1+0.11)^2+DCF!$B$2*(1+$A6)^3/(1+0.11)^3+DCF!$B$2*(1+$A6)^4/(1+0.11)^4+DCF!$B$2*(1+$A6)^5/(1+0.11)^5 +(DCF!$B$2*(1+$A6)^5*1.03/(0.11-0.03))/(1+0.11)^5-DCF!$B$4)/DCF!$B$3*DCF!$B$6
A7: 0.12 | B7: =( DCF!$B$2*(1+$A7)^1/(1+0.08)^1+DCF!$B$2*(1+$A7)^2/(1+0.08)^2+DCF!$B$2*(1+$A7)^3/(1+0.08)^3+DCF!$B$2*(1+$A7)^4/(1+0.08)^4+DCF!$B$2*(1+$A7)^5/(1+0.08)^5 +(DCF!$B$2*(1+$A7)^5*1.03/(0.08-0.03))/(1+0.08)^5-DCF!$B$4)/DCF!$B$3*DCF!$B$6 | C7: =( DCF!$B$2*(1+$A7)^1/(1+0.09)^1+DCF!$B$2*(1+$A7)^2/(1+0.09)^2+DCF!$B$2*(1+$A7)^3/(1+0.09)^3+DCF!$B$2*(1+$A7)^4/(1+0.09)^4+DCF!$B$2*(1+$A7)^5/(1+0.09)^5 +(DCF!$B$2*(1+$A7)^5*1.03/(0.09-0.03))/(1+0.09)^5-DCF!$B$4)/DCF!$B$3*DCF!$B$6 | D7: =( DCF!$B$2*(1+$A7)^1/(1+0.1)^1+DCF!$B$2*(1+$A7)^2/(1+0.1)^2+DCF!$B$2*(1+$A7)^3/(1+0.1)^3+DCF!$B$2*(1+$A7)^4/(1+0.1)^4+DCF!$B$2*(1+$A7)^5/(1+0.1)^5 +(DCF!$B$2*(1+$A7)^5*1.03/(0.1-0.03))/(1+0.1)^5-DCF!$B$4)/DCF!$B$3*DCF!$B$6 | E7: =( DCF!$B$2*(1+$A7)^1/(1+0.11)^1+DCF!$B$2*(1+$A7)^2/(1+0.11)^2+DCF!$B$2*(1+$A7)^3/(1+0.11)^3+DCF!$B$2*(1+$A7)^4/(1+0.11)^4+DCF!$B$2*(1+$A7)^5/(1+0.11)^5 +(DCF!$B$2*(1+$A7)^5*1.03/(0.11-0.03))/(1+0.11)^5-DCF!$B$4)/DCF!$B$3*DCF!$B$6
